colltools/__init__.py
tests/__init__.py
tests/test_batch.py
colltools-1.0.4.dist-info/LICENCE
colltools-1.0.4.dist-info/METADATA
colltools-1.0.4.dist-info/WHEEL
colltools-1.0.4.dist-info/top_level.txt
colltools-1.0.4.dist-info/RECORD
