Metadata-Version: 2.1
Name: colltools
Version: 1.0.4
Summary: Tools for iterating and working with collections
Home-page: https://github.com/JakubTesarek/colltools
Author: Jakub Tesárek
Author-email: jakub@tesarek.me
License: APACHE LICENSE 2.0
Keywords: itertools collections iteration
Platform: UNKNOWN
Classifier: Development Status :: 4 - Beta
Classifier: License :: OSI Approved :: Apache Software License
Classifier: Intended Audience :: Developers
Classifier: Programming Language :: Python :: 3.6
Classifier: Programming Language :: Python :: 3.7
Requires-Python: >=3.6
Provides-Extra: test
Requires-Dist: pytest ; extra == 'test'
Requires-Dist: pytest-cov ; extra == 'test'
Requires-Dist: codecov ; extra == 'test'
Requires-Dist: mypy ; extra == 'test'
Requires-Dist: pylint ; extra == 'test'
Requires-Dist: sphinx ; extra == 'test'
Requires-Dist: sphinxcontrib-spelling ; extra == 'test'
